{
    "$schema": "https://schema.management.azure.com/schemas/2019-04-01/deploymentParameters.json#",
    "contentVersion": "1.0.0.0",
    "parameters": {
        "environmentType": {
            "value": "prod"
        },
        "postgreSQLServerName": {
            "value": "team3-dbsrv-prod"
        },
        "postgreSQLDatabaseName": {
            "value": "team3-db-prod"
        },
        "appServicePlanName": {
            "value": "team3-asp-prod"
        },
        "appServiceAPIAppName": {
            "value": "team3-be-prod"
        },
        "appServiceAppName": {
            "value": "team3-fe-prod"
        },
        "azureMonitorName": {
            "value": "team3-am-prod"
          },
        "location": {
            "value": "eastasia"
        },
        "acrname": {
            "value": "team3acrprod"
        },
        "staticSiteName": {
            "value": "team3-staticsite-prod"
        },
        "appServicePlanNamedtest":{ 
            "value": "team3asp-prod"
        },
        "sku": {
            "value": {
                "capacity": 4,
                "family": "S",
                "name": "S1",
                "size": "S1",
                "tier": "Standard"
              }
        },
        "appInsightsName": {
            "value": "team3-ai-prod"
        },
        "keyVaultName": {
            "value": "team3-kv-prod"
        }
    }
}